Workbook

Sheet Form Responses 1
A1: Timestamp | B1: PROGRAM | C1: SECTION | D1: Fullname Ex: Juan D. Cruz | E1: Name of Sender (Gcash) | F1: Reference No. of Payment | G1: Proof of Payment Upload here your screenshot as proof of payment. | H1: Gcash Number | I1: Column 8 | J1: Type number of keychain/s you want purchase and pay on June 18 after the Hooding Ceremony. | K1: Payment method | L1: Gcash Number | M1: Number | N1: Found in Gcash & Refunded 210 | O1: Not found in Gcash
A2: 45806.886 | B2: Bachelor of Science in Information Technology | C2: 4-IT1 | D2: John Paul Galido | E2: Lorie Erasga | F2: 00000000 | G2: https://drive.google.com/open?id=14fQzuzVx3BednIKmRUXookodJcud30yR
A3: 45808.573 | B3: Bachelor of Elementary Education (BEED) | C3: 4-EED2 | D3: LENNEL D. GRANDE | E3: ARNEL GRANDE | F3: 8029 211 774207 | G3: https://drive.google.com/open?id=1TcawMF3LlJ7C6v7gAlIv95QSJrl7-jmz | L3: 09305424246 | M3: 1
A4: 45809.533 | B4: Bachelor of Science in Information Technology | C4: 4 IT - 1 | D4: Danyca Alliah Villanueva | E4: Danyca Alliah Villanueva | F4: 6029244266398 | G4: https://drive.google.com/open?id=1cRelER2Xgs5jfif4YFr84iFPYJqaUsLB | L4: 09258471460 | M4: 1
A5: 45809.578 | B5: Bachelor of Science in Information Technology | C5: 4IT-4 | D5: Dianne T. Domingo | E5: Dianne Domingo | F5: 1029246322521 | G5: https://drive.google.com/open?id=1UbatZ5wGsBhPXbVwbQhNcOZatt0KBPAn | L5: 09955116313 | M5: 1
A6: 45809.609 | B6: Bachelor of Elementary Education (BEED) | C6: EED3 | D6: Mary Grace V. Lastre | E6: Mary Grace Lastre | F6: 0029247709648 | G6: https://drive.google.com/open?id=19U8DfOMyaNco4fU9_rPXy2TYDZPoErC4 | L6: 09667742796 | M6: 1
A7: 45809.989 | B7: Bachelor of Elementary Education (BEED) | C7: 4-Eed1 | D7: Fiona May Anne L. San Diego | E7: Fiona May Anne L. San Diego | F7: 1029264976605 | G7: https://drive.google.com/open?id=1QdQyTIShfgaJvcgloNv2UG5wBZ8IkcDX | L7: 09065558912 | M7: 1
A8: 45811.761 | B8: Bachelor of Secondary Education Major in English (BSED-E) | C8: 4-SEDE1 | D8: Chelo Mae B. Arrogante | E8: Chelo Mae Arrogante | F8: 9029315561063 | G8: https://drive.google.com/open?id=1uNNuBOxtoMYjufu8PGb-tYPNI-T9XaD- | M8: 1
A9: 45811.769 | B9: Bachelor of Secondary Education Major in English (BSED-E) | C9: 4-SEDE1 and 4-SEDE2 | D9: Sarah Joy Mangeron, Ingrid Montero, Chelo Mae Arrogante, Daphne June Durias, Dezerie Mae Amongan, Janna Marie Felias, Maxxieline Dela Cruz | E9: Maxxieline D. | F9: 1029321287492 | G9: https://drive.google.com/open?id=1zrc0IeZpZJutb-_FxqffZESnyWLUIal7 | M9: 7
A10: 45811.772 | B10: Bachelor of Secondary Education Major in English (BSED-E) | C10: 4-SEDE2 | D10: Jean Ivy G. Fresnido | E10: Jean Ivy Fresnido | F10: 5029 321 285188 | G10: https://drive.google.com/open?id=18ZpR4IbtU-DQOuQw7b6CyH3UyRpWAINK | M10: 1
A11: 45811.775 | B11: Bachelor of Secondary Education Major in English (BSED-E) | C11: 4-SEDE1 | D11: Cyril Del Valle | E11: Jamaica Banaticla | F11: 2029-321-484664 | G11: https://drive.google.com/open?id=1ZzWic2hxyDi2EkD1hUxMkXEKJtx1-Xte | M11: 1
A12: 45811.788 | B12: Bachelor of Secondary Education Major in English (BSED-E) | C12: 4-SEDE1 | D12: Sarah Joy H. Mangeron | E12: Sarah Joy M. | F12: 1029 313 458219 | G12: https://drive.google.com/open?id=1GV5mm8wcAslIF5uOCTzPm7_Lxx5A0xa9 | M12: 1
A13: 45811.79 | B13: Bachelor of Secondary Education Major in English (BSED-E) | C13: 4-SEDE2 | D13: Lhyn Marie P. Tabieros | E13: Lhyn Marie T | F13: 9029 322 399032 | G13: https://drive.google.com/open?id=1jOqW_cPskhH8CKW9XwaUOOh8urL9lcNM | M13: 1
A14: 45811.795 | B14: Bachelor of Secondary Education Major in English (BSED-E) | C14: 4SEDE1 | D14: Aubrey A. Pielago | E14: Mariesol B. | F14: 4029 322 666870 | G14: https://drive.google.com/open?id=1lQiq612rMURgpKgWVFq3P6Kn2WXPocRH | M14: 1
A15: 45811.804 | B15: Bachelor of Secondary Education Major in English (BSED-E) | C15: SEDE1 | D15: Jemelyn C. Desacula | E15: Juliana Marie C. Desacula | F15: 5029323126797 | G15: https://drive.google.com/open?id=10em77mRbSyHiEufzlTEvMgrmvG3Qi6fc | M15: 1
A16: 45811.81 | B16: Bachelor of Secondary Education Major in English (BSED-E) | C16: 4-SEDE1 | D16: Ingrid C. Montero | E16: Ma.Victoria Montero | F16: 7029315441811 | G16: https://drive.google.com/open?id=1mtuf9V_juxemr7HNVDfK8mRo-E-uwXlu | M16: 1
A17: 45811.826 | B17: Bachelor of Secondary Education Major in English (BSED-E) | C17: 4-SEDE2 | D17: Dezerie Mae L. Amongan | E17: Esperanza Amongan | F17: 5029 316 401888 | G17: https://drive.google.com/open?id=10qCvKcF8HW5MADvK2OEYtY9COQW3v4Qp | M17: 1
A18: 45811.86 | B18: Bachelor of Elementary Education (BEED) | C18: 4EED4 | D18: Robe Yuan P. Benito | E18: Lilibeth Benito | F18: 4029 325 981662 | G18: https://drive.google.com/open?id=11-T1a-VMI0tT-TPW_ZI0sH0udU25-gGr | M18: 1
A19: 45811.889 | B19: Bachelor of Secondary Education Major in English (BSED-E) | C19: 4SEDE-2 | D19: Arbie M. Crazo | E19: ARBIE C. | F19: 5029327375842 | G19: https://drive.google.com/open?id=1FcV50WNuXyvTESFlX7L1FLySBrWXyQ3D | M19: 1
A20: 45811.958 | B20: Bachelor of Secondary Education Major in English (BSED-E) | C20: SEDE—2 | D20: Mara Charisma A. Suarez | E20: John Edward Mayuga | F20: 2029 329 861078 | G20: https://drive.google.com/open?id=1OrmijUWeLBv6rFemA9ntZnj14V18DFu8 | M20: 1
A21: 45812.321 | B21: Bachelor of Science in Information Technology | C21: 4- IT1 | D21: Leah Marie M. Ferares | E21: Aberde Leo | F21: 0029 334 765119 | G21: https://drive.google.com/open?id=16M2bh30mvREy4nvP7TrIDE9Cg-piF6Tq | M21: 1
A22: 45812.379 | B22: Bachelor of Science in Information Technology | C22: 4-IT1 | D22: Jerome M. Lubrin | E22: JEROME L. | F22: 1029 336 504149 | G22: https://drive.google.com/open?id=1GK3aNDIuNMLOZ7BVfgzxKodxQcQCfH0D | M22: 1
A23: 45812.386 | B23: Bachelor of Science in Information Technology | C23: 4IT-1 | D23: Cristina S. Equial | E23: Cristina E. | F23: 1029336740245 | G23: https://drive.google.com/open?id=19L1Oj1qIbnQzaHvskLw2KIPpB0_ZuFjJ | M23: 1
A24: 45812.406 | B24: Bachelor of Science in Information Technology | C24: IV-IT1 | D24: Paul Ivan A. Arazo | E24: Paul Ivan A. Arazo | F24: 0029337486691 | G24: https://drive.google.com/open?id=10Xqy-HXUeQ5kzVvu-ZJhIvM4hHGRcJ8I | M24: 1
A25: 45812.408 | B25: Bachelor of Science in Accounting Information System | C25: 4-IT1 | D25: Anna Grace M. Rosco | E25: Anna Grace Rosco | F25: 1029 337 578059 | G25: https://drive.google.com/open?id=1q6tjWZHmvUAaQdn8dnhH_rblkXgOe5R8 | M25: 1
A26: 45812.422 | B26: Bachelor of Elementary Education (BEED) | C26: EED4 | D26: Justine A. Bandales | E26: Justine A. Bandales | F26: 7029 338 115436 | G26: https://drive.google.com/open?id=1rLNHKdhBdv1yTvwFHHFXODZQu_frrz5W | M26: 1
A27: 45812.424 | B27: Bachelor of Science in Computer Science | C27: 4-CS2 | D27: Lloyd Anthony Hontiveros | E27: Lloyd Anthony Hontiveros | F27: 5029 338 230120 | G27: https://drive.google.com/open?id=1W2m1y0z2eZSXObX6XL3RLb5OYu9ok-yq | M27: 1
A28: 45812.428 | B28: Bachelor of Secondary Education Major in English (BSED-E) | C28: 4-SEDE1 | D28: Kristine T. Oruga | E28: Kristine Oruga | F28: 4029 338 289102 | G28: https://drive.google.com/open?id=1egCZgI3Jd15h0h-psuwVcxPdx30gA6ax | M28: 1
A29: 45812.437 | B29: Bachelor of Secondary Education Major in English (BSED-E) | C29: 4-SEDE1 | D29: Tengco, Nixon D. | E29: Nixon Tengco | F29: 5029338794365 | G29: https://drive.google.com/open?id=1WJdxqeKkxG_9YOBdF1T3Gwb9TT2sV4mS | M29: 1
A30: 45812.448 | B30: Bachelor of Secondary Education Major in English (BSED-E) | C30: 4-SEDE1 | D30: Bernalet S. Matanguihan | E30: Jayvie Matanguihan | F30: 0029 339 223795 | G30: https://drive.google.com/open?id=1EqnGuQRgLWv_DcGQI9WjjYmL4fVGyNyJ | M30: 1
A31: 45812.462 | B31: Bachelor of Science in Accountancy | C31: A6 | D31: Mary Jane S. Arcansalin | E31: Mary Jane Arcansalin | F31: 0029339819752 | G31: https://drive.google.com/open?id=1N0jIasobyJRK10gM3i-XWS_aS1IKmC4T | M31: 1
A32: 45812.483 | B32: Bachelor of Science in Computer Science | C32: 4-cs3 | D32: Judy Anne S. Ortile | E32: Judy Anne S. Ortile | F32: 8029340710172 | G32: https://drive.google.com/open?id=1hHXMgChHrwO6HfxkXek1SQDvBfwRf77i | M32: 1
A33: 45812.509 | B33: Bachelor of Science in Accountancy | C33: 4-A3 | D33: Charisse Mae R. Cardiño | E33: Charisse Mae Cardiño | F33: 9029341831221 | G33: https://drive.google.com/open?id=1KSYrOOY4zVDyYchfjl21mpa9FEugXFgU | M33: 1
A34: 45812.585 | B34: Bachelor of Secondary Education Major in English (BSED-E) | C34: 4SEDE 1 | D34: Glamirose U. Napiza | E34: Glamirose Napiza | F34: 9029344997487 | M34: 1
A35: 45812.59 | B35: Bachelor of Secondary Education Major in Science (BSED-S) | C35: 4SEDS-2 | D35: Shyla Marie M. Buseta | E35: Shyla Marie M. Buseta | F35: 7029345333604 | G35: https://drive.google.com/open?id=1TU180I7XuHKhnSDTDQiMgpiituZT9bXr | M35: 1
A36: 45812.6 | B36: Bachelor of Science in Accountancy | C36: 4-A3 | D36: Mariel Joy M. Mayor | E36: Mariel Joy Mayor | F36: 6029345708791 | G36: https://drive.google.com/open?id=11AtJk9KnYXNR5KmBPJZJU8GSUozSxGEM | M36: 1
A37: 45812.61 | B37: Bachelor of Science in Accountancy | C37: 4-A4 | D37: Pauline B. Tingzon | E37: Pauline Tingzon | F37: 6029346142477 | G37: https://drive.google.com/open?id=1_5TAGkZkeksHvgBJcqNngINV1CBOe_kY | M37: 1
A38: 45812.623 | B38: Bachelor of Science in Accountancy | C38: 4-A6 | D38: Bernadette R. Arboleda | E38: Bernadette Arboleda | F38: 7029346693403 | G38: https://drive.google.com/open?id=1kFxDAB0Bhvn6OS58_xD9PaFulZ_tGiNv | M38: 1
A39: 45812.718 | B39: Bachelor of Elementary Education (BEED) | C39: Eed2 | D39: Jackie N. Carandang | E39: Jackie N. Carandang | F39: 8029350742467 | G39: https://drive.google.com/open?id=1R2m97vjM5VRgKTSp45TtDAvlDEipcX1W | M39: 1
A40: 45812.753 | B40: Bachelor of Elementary Education (BEED) | C40: 4-EED1 | D40: Michael C. Valenzuela | E40: John Arman P. Baldonado | F40: 2029352578573 | G40: https://drive.google.com/open?id=1TW1hD0sqh-8uXMRQiGCyx6y05nozki49 | M40: 1
A41: 45812.759 | B41: Bachelor of Elementary Education (BEED) | C41: 4eed4 | D41: Christine Marie C. Bakilid | E41: Christine Marie C. Bakilid | F41: 1029352869374 | G41: https://drive.google.com/open?id=1WabWeJAf-l5DZnLsiR2Xo_RnhOwS9Op9 | M41: 1
A42: 45812.76 | B42: Bachelor of Elementary Education (BEED) | C42: 4-EED2 | D42: Argelle Ann Sierra | E42: Argelle Ann Sierra | F42: 4029-352-925659 | G42: https://drive.google.com/open?id=1eI_dqsLGLaZP0lr-Pmlw4zX2b4TABqYz | M42: 1
A43: 45812.774 | B43: Bachelor of Elementary Education (BEED) | C43: IV- EED2 | D43: Sophia Reign N. Oropesa+ | E43: Rosie Oropesa | F43: 3029353411927 | G43: https://drive.google.com/open?id=1T3X6Iq9ZIo6vhQ8qX5UCWFhSS5KIDlUM | M43: 1
A44: 45812.818 | B44: Bachelor of Secondary Education Major in English (BSED-E) | C44: 4-SEDE2 | D44: Alliana Mae D. De Gula | E44: . | F44: 8029 354 239913 | G44: https://drive.google.com/open?id=14MBrT075p_ADI_QJg8G8-oUJwTe-coEY | H44: . | M44: 1
A45: 45812.823 | B45: Bachelor of Science in Information Technology | C45: 4-IT1 | D45: Ma. Nicole A. Babadilla | E45: Ma. Nicole A. Babadilla | F45: 0029 356 240384 | G45: https://drive.google.com/open?id=1HEOW3X9n5skFzbPDYeMpvSDfUvQt3shz | H45: 09928468524 | M45: 1
A46: 45812.824 | B46: Bachelor of Secondary Education Major in Mathematics (BSED-M) | C46: IV-SEdM1 | D46: Julie Jane Bilolo | E46: Julie Jane Bilolo | F46: 9029 356 342767 | G46: https://drive.google.com/open?id=1ZXiCBdRfoqp4nUEK4bL4T-jsUbHe2Csd | H46: 09636858519 | M46: 1
A47: 45812.833 | B47: Bachelor of Secondary Education Major in English (BSED-E) | C47: 4-SEDE1 | D47: Jenneth M. Sequete | E47: Mary Grace O. | F47: 9029 356 638197 | G47: https://drive.google.com/open?id=1FSoFlacf-th0eLliuEh50iMt1daY-lhq | H47: 09359109141 | M47: 1
A48: 45812.867 | B48: Bachelor of Secondary Education Major in English (BSED-E) | C48: 4-SEDE2 | D48: Kaye Zaira C. Sumicad | E48: Emelita Sumicad | F48: 7029358417411 | G48: https://drive.google.com/open?id=1ETsvftwUwQPLsbZKwrm_qMQtsqrE2L6O | H48: 09538110972 | M48: 1
A49: 45812.88 | B49: Bachelor of Secondary Education Major in English (BSED-E) | C49: 4-SEDE2 | D49: Mayden D. Corilla | E49: Mayden Corilla | F49: 4029 359 105564 | G49: https://drive.google.com/open?id=1PfZ6v7qaO_xwNCs0zHQ8JyquPZOqmPN6 | H49: 09196981274 | M49: 1
A50: 45812.94 | B50: Bachelor of Elementary Education (BEED) | C50: 4-EED4 | D50: Mheagan B. Dacutanan | E50: Maria Dacutanan | F50: 5029361486275 | G50: https://drive.google.com/open?id=1q3BUcoEFFbvjZsXtYip0QP0j3L3-sKRz | H50: 09166891818 | M50: 1
A51: 45813.337 | B51: Bachelor of Secondary Education Major in English (BSED-E) | C51: 4-SEDE1 | D51: Ma. Cristy Y. Pujalte | E51: Janet Pujalte | F51: 6029 367 276588 | G51: https://drive.google.com/open?id=14w1YAt8ULrja7zvaOFl2oRSsKOrNFCpd | H51: 09212172682 | M51: 1
A52: 45813.38 | B52: Bachelor of Science in Accountancy | C52: A6 | D52: Joy-Ann E. Rubio | E52: Joy ann rubio | F52: 8029 368 838672 | G52: https://drive.google.com/open?id=1m_p66FANV6-SDdYGuV9POYCzfsvC2DWU | H52: 09675618289 | M52: 1
A53: 45813.412 | B53: Bachelor of Elementary Education (BEED) | C53: EED2 | D53: Miracle Irish Gavarra | E53: Miracle Irish Gavarra | F53: 4029 369 992540 | G53: https://drive.google.com/open?id=1cxLWUZjk9pMwIm0TTA7djpL1mjOAGs8l | H53: 09918024017 | M53: 1
A54: 45813.459 | B54: Bachelor of Elementary Education (BEED) | C54: 4-EED2 | D54: Christine Joy B. Felipe | E54: Christine Joy Felipe | F54: 2029372013262 | G54: https://drive.google.com/open?id=1iykx-HhuSz7kTNEQcDXTDIqyrVYSRQ2F | H54: 09106884577 | M54: 1
A55: 45813.562 | B55: Bachelor of Science in Information Technology | C55: IT-3 | D55: Jerico A. Ventura | E55: Jerico V. | F55: 3029 376 593094 | G55: https://drive.google.com/open?id=1thJatTVKXnMrSlb-5Wv9iWfySb2wCxe6 | H55: 09479677452 | M55: 1
A56: 45813.593 | B56: Bachelor of Secondary Education Major in English (BSED-E) | C56: 4-SEDE2 | D56: Julia May M. Balag | E56: Maxxieline D. | F56: 1029 367 590457 | G56: https://drive.google.com/open?id=1IH1VnBVT8W-pCkyz4dz0xpXsoYDL65o2 | H56: 09760392348 | M56: 1
A57: 45813.626 | B57: Bachelor of Science in Information Technology | C57: 4-IT1 | D57: Jethro R. Frane | E57: Jethro Frane | F57: 0029379407183 | G57: https://drive.google.com/open?id=1EwhXvDf3oQB7dj9BIpYhlTaGool0sGnj | H57: 0976 109 8047 | M57: 1
A58: 45813.636 | B58: Bachelor of Secondary Education Major in English (BSED-E) | C58: 4SEDE2 | D58: Mica Ella D. Mateo | E58: Amiel Medalla | F58: 6029357373658 | G58: https://drive.google.com/open?id=1T_-QHavWSIDiv2xAhJIaWqwA_cssxwLK | H58: 09614175849 | M58: 1
A59: 45813.655 | B59: Bachelor of Science in Information Technology | C59: 4-IT | D59: Bernadette Fopalan | E59: Bernadette Fopalan | F59: 258040 | G59: https://drive.google.com/open?id=1oqps1M7T_EK88eLMym_kCq1sPYHzrdXo | H59: 09929058054 | M59: 1
A60: 45813.656 | B60: Bachelor of Science in Information Technology | C60: IT-3 | D60: EVANGELISTA CHERRY M. | E60: Cherry Evangelista | F60: 9029 380 782555 | G60: https://drive.google.com/open?id=1UOYCq7eFnVcw_kEpPfMLc1SDWoh9P0qm | H60: 09760274585 | M60: 1
A61: 45813.657 | B61: Bachelor of Science in Information Technology | C61: IT-2 | D61: Junievil M. Tamsi | E61: Junievil Tamsi | F61: 2029 380 800797 | G61: https://drive.google.com/open?id=1OkznGtJEgqD7OH2SQncAuL2FhK5PiSfk | H61: 09932535210 | M61: 1
A62: 45813.657 | B62: Bachelor of Science in Information Technology | C62: IT 3 | D62: Racel Nean O. Padoc | E62: Racel Nean Padoc | F62: 5029 380 830614 | G62: https://drive.google.com/open?id=1QWYpr7Hg6A3YEqzGFxmy_oVzSFe96njq | H62: 09567299904 | M62: 1
A63: 45813.662 | B63: Bachelor of Science in Information Technology | C63: 4-IT1 | D63: Jeffrey C. Regalario | E63: Jeffrey Regalario | F63: 5029 381 009995 | G63: https://drive.google.com/open?id=1Hu_bQrwJd2ikPoB9w833S18ha580q2cf | H63: 09761247202 | M63: 1
A64: 45813.664 | B64: Bachelor of Elementary Education (BEED) | C64: IV-EED2 | D64: Erika Gwyneth G. Esplana | E64: Gloribel Esplana | F64: 8029 381 045232 | G64: https://drive.google.com/open?id=1JkqE8-8yXd1j30sk-xo_E5tC6_GwUxa- | H64: 09774772134 | M64: 1
A65: 45813.665 | B65: Bachelor of Science in Information Technology | C65: IT-2 | D65: Princess D. Castillo | E65: Junievil Tamsi | F65: 2029 381 153176 | G65: https://drive.google.com/open?id=1lFDuLC1A_Ea3mvhXudFF_-Y0FuX6Hpb9 | H65: 09932535210 | M65: 1
A66: 45813.672 | B66: Bachelor of Science in Information Technology | C66: 4-IT2 | D66: Ralph Louis M. Obispo | E66: Archie Obispo | F66: 9029381465567 | G66: https://drive.google.com/open?id=1WwrOndBiFRYVOsIRGGY6q5aETR3hH2rO | H66: 09385826535 | M66: 1
A67: 45813.673 | B67: Bachelor of Science in Information Technology | C67: 4-IT 2 | D67: Ryan R. Ofalsa | E67: Ryan Ofalsa | F67: 1029 381 536109 | G67: https://drive.google.com/open?id=1dAKJiF4K2VNp3wg89CEe7QUXcXfdx1ml | H67: 09947438623 | M67: 1
A68: 45813.679 | B68: Bachelor of Science in Information Technology | C68: 4-IT2 | D68: Christallyn O. Frianeza | E68: Sonny Frianeza | F68: 3029381465901 | G68: https://drive.google.com/open?id=1Z_tF8oeXrXKuuDb2rvgO_zj8A1kOTzFn | H68: 09753901568 | M68: 1
A69: 45813.685 | B69: Bachelor of Science in Information Technology | C69: 4-IT2 | D69: Ailyn R. Manjares | E69: Ailyn Manjares | F69: 3029-382-067838 | G69: https://drive.google.com/open?id=1yoS4uDgxnIWt9iba3WdzJmtt36nruZWZ | H69: 09085489935 | M69: 1
A70: 45813.686 | B70: Bachelor of Science in Information Technology | C70: 4BSIT-1 | D70: Jose Carlo Habacon Arintoc | E70: Jose Carlo H. Arintoc | F70: 3029 382 155651 | G70: https://drive.google.com/open?id=1guXEe5vwzdoRfMboKwnz-NoGZBbu5Xsg | H70: 09474413295 | M70: 1
A71: 45813.734 | B71: Bachelor of Secondary Education Major in Science (BSED-S) | C71: 4SEDS2 | D71: Mary Joyce Narise T. Reblando | E71: Mary Joyce Narise Reblando | F71: 5029 384 552701 | G71: https://drive.google.com/open?id=1qUKOv2T_pmfMCURw8ZddscZR0k68aupx | H71: 09511526267 | M71: 1
A72: 45813.834 | B72: Bachelor of Science in Information Technology | C72: IV - IT I | D72: Pamela Joy L. Bien | E72: Pamela Joy Bien | F72: 5029389843655 | G72: https://drive.google.com/open?id=1cJCSZnL67QXb44HW4whgZxqzyQiuVZxH | H72: 09059213014 | M72: 1
A73: 45813.912 | B73: Bachelor of Secondary Education Major in English (BSED-E) | C73: 4SEDE-2 | D73: Marielle Kathleen M. Perez | E73: Marielle Perez | F73: 760471 | G73: https://drive.google.com/open?id=1kJ9yuskV2TgoyghnjteZ6ZTWks3l4U4T | H73: 09923480184 | M73: 1
A74: 45813.961 | B74: Bachelor of Secondary Education Major in English (BSED-E) | C74: 4-SEDE1 | D74: Cristine Joy M. Reboltan | E74: Elisa Laranjo | F74: 0029 395 615690 | G74: https://drive.google.com/open?id=1F-Z-k5e5qoiY3OkKfasH7ANN3VEN3YPE | H74: 09665634578 | M74: 1
A75: 45813.969 | B75: Bachelor of Secondary Education Major in English (BSED-E) | C75: 4-SEDE1 | D75: Jizelle A. Martinez | E75: Jhamie Anne Martinez | F75: 7029 395 868576 | G75: https://drive.google.com/open?id=1UCpt0rSFlYwkNTnUVcsx9NO912-PCxya | H75: 09934332618 | M75: 1
A76: 45814.332 | B76: Bachelor of Secondary Education Major in English (BSED-E) | C76: 4-SEDE2 | D76: Jojie May T. Colongan | E76: Sheila May C | F76: 8029 394 648113 | G76: https://drive.google.com/open?id=1n-RDqtqdDxNxci3cmRQMYlP3yWoIoNiI | H76: 09335969036 | M76: 1
A77: 45814.348 | B77: Bachelor of Secondary Education Major in English (BSED-E) | C77: 4-SEDE2 | D77: Cailyn Fae L. Canicon | E77: Cailyn Fae Canicon | F77: 2029 401 555126 | G77: https://drive.google.com/open?id=1KQbvB2dGDMSO2WnSbwnL-orf9Q-tJjpv | H77: 09477476197 | M77: 1
A78: 45814.363 | B78: Bachelor of Elementary Education (BEED) | C78: 4EED-2 | D78: Shimei C. Canave | E78: Shimei Canave | F78: 3029 402 038930 | G78: https://drive.google.com/open?id=104LDM0IzF7VW32qjrLqAkyE3qLfWzH6i | H78: 09921498992 | M78: 1
A79: 45814.378 | B79: Bachelor of Elementary Education (BEED) | C79: 4-EED3 | D79: Russel Ann S. Mabilangan | E79: Russel Ann Mabilangan | F79: 6049 402 578364 | G79: https://drive.google.com/open?id=1fIzokkaWwZaAHhBFUy2PA0gl6x6pa7A1 | H79: 09858045093 | M79: 1
A80: 45814.381 | B80: Bachelor of Elementary Education (BEED) | C80: EED1 | D80: Mary Rose D. Javier | E80: Mary Rose Javier | F80: 4029 402 656425 | G80: https://drive.google.com/open?id=1XOYVlW9oGxbvN3-qnoMagqtmhOSdhVGk | H80: 09551625297 | M80: 1
A81: 45814.398 | B81: Bachelor of Elementary Education (BEED) | C81: 4-EED2 | D81: Czarina Elaine Z. Ribleza | E81: Czarina Ribleza | F81: 8029403318280 | G81: https://drive.google.com/open?id=1UWhTYqOHHMgA3gnl_YdJXW2iMo2GsbDi | H81: 09665506242 | M81: 1
A82: 45814.412 | B82: Bachelor of Science in Information Technology | C82: IV-IT1 | D82: Bernadette V. Tanhueco | E82: Bernadette Tanhueco | F82: 1029 403 781693 | G82: https://drive.google.com/open?id=1WB2nCykTIV5NNDr6m2aOeCH_GpN8FJp7 | H82: 09519750242 | M82: 1
A83: 45814.457 | B83: Bachelor of Elementary Education (BEED) | C83: 4-EED4 | D83: Ma. Regina A. Ferreras | E83: Ma. Regina Ferreras | F83: Ref No. 6029405686192 | G83: https://drive.google.com/open?id=1fEkoaVQLe9hGIrzvvnBnpHNWLOAwl3H4 | H83: 09761753197 | M83: 1
A84: 45814.483 | B84: Bachelor of Science in Computer Science | C84: 4CS-1 | D84: Harold G. Hayagan | E84: Harold Hayagan | F84: 8029406538263 | G84: https://drive.google.com/open?id=1W5_v1wJPGJYc0i5XvWrtTR5T3rFnAGVv | H84: 09941701252 | M84: 1
A85: 45814.485 | B85: Bachelor of Elementary Education (BEED) | C85: 2-EED2 | D85: Cyra Jean S. Narvaja | E85: Cyra Jean S. Narvaja | F85: 8029 406 970742 | G85: https://drive.google.com/open?id=1rjsStw3ZT6wXCQ_q9jxiPK1g0qlOKZ4E | H85: 9701385500 | M85: 1
A86: 45814.487 | B86: Bachelor of Science in Computer Science | C86: 4CS3 | D86: Claire T. Salazar | E86: Claire Salazar | F86: 2029407044084 | G86: https://drive.google.com/open?id=1qUHO9v96CKhwb53mB74R-DG-_RGWmHR6 | H86: 09219542635 | M86: 1
A87: 45814.556 | B87: Bachelor of Secondary Education Major in Mathematics (BSED-M) | C87: 4-SEDM1 | D87: Ma. Aurora Dianna E. Atanacio | E87: Ma. Aurora Dianna Atanacio | F87: 7029410132411 | G87: https://drive.google.com/open?id=1DlFWojR6pBx5Ey-9uhTzjxivxsvxYpcL | H87: 0992-992-7280 | M87: 1
A88: 45814.576 | B88: Bachelor of Science in Computer Science | C88: 4-CS2 | D88: Timothy Jake D. Del Mundo | E88: Timothy Jake Del Mundo | F88: 6029410994165 | G88: https://drive.google.com/open?id=1oCIYBhkD39snMr1uuy5JNxFL4WT3u8TU | H88: 09503426942 | M88: 1
A89: 45814.586 | B89: Bachelor of Science in Computer Science | C89: CS1 | D89: Christian Genesis A. Medina | E89: Christian Genesis Medina | F89: 3029 411 406255 | G89: https://drive.google.com/open?id=19dOv0Cq3Q0c6D516SSYlQitqB8_-AO1c | H89: 09622848997 | M89: 1
A90: 45814.623 | B90: Bachelor of Science in Accountancy | C90: A4 | D90: Eshiel Mae D. Alano | E90: Helen Alano | F90: 2029412949706 | G90: https://drive.google.com/open?id=1JJV_NIAv4BpuDqVGZZe9BF7MI9-YaM-1 | H90: 09931145082 | M90: 1
A91: 45814.632 | B91: Bachelor of Science in Accountancy | C91: A1 | D91: Elliemer R. Rocello | E91: Emerson Rocello | F91: 1029 413 345806 | G91: https://drive.google.com/open?id=1zNeBCAbvG5zq8Ulctets-uvgAOrZSDdS | H91: 09269513992 | M91: 1
A92: 45814.644 | B92: Bachelor of Science in Accountancy | C92: A4 | D92: Sakura A. Takata | E92: Princess Angelo | F92: 2029413849647 | G92: https://drive.google.com/open?id=1aUs71EUQHfncsg3N8grL0HdTNn8NqAio | H92: 09656447435 | M92: 1
A93: 45814.656 | B93: Bachelor of Science in Accounting Information System | C93: 4-AIS1 | D93: Ashley M. Domingo | E93: Ashley D. | F93: 7029414312340 | G93: https://drive.google.com/open?id=1yOeLBDbhs-CKAMXt1rNriBJhx9AhsjZH | H93: 09100412692 | M93: 1
A94: 45814.689 | B94: Bachelor of Science in Accountancy | C94: 4-A3 | D94: Rovea P. Domer | E94: Cash madam | F94: N/a | G94: https://drive.google.com/open?id=1QQnGyuGvNiBQDpnzeVnmS_1MlrPz4FWT | H94: N/a | J94: 1 | K94: Cash (Upon claiming on June 18) | M94: =if(K94="GGash",1,0) -> 0
A95: 45814.69 | B95: Bachelor of Science in Accountancy | C95: 4-A2 | D95: Alyana Cheska L. Humarang | E95: . | F95: . | G95: https://drive.google.com/open?id=1CTkQtapd5MAHVyofaPiLUk4Hsu4DyOcV | H95: . | J95: 1 | K95: Cash (Upon claiming on June 18) | M95: =if(K95="GGash",1,0) -> 0
A96: 45814.696 | B96: Bachelor of Science in Accountancy | C96: 4-A1 | D96: Cathlyn Kaye B. Alday | E96: Cathlyn Kaye Alday | F96: 3029415855703 | G96: https://drive.google.com/open?id=1HAXNu_xFmnUQlFZ9B-I64EsC6gl-hcRv | H96: 09668452385 | J96: 1 | K96: GGash | M96: =if(K96="GGash",1,0) -> 1
A97: 45814.696 | B97: Bachelor of Science in Accounting Information System | C97: 4-AIS1 | D97: Cera S. Olitoquit | J97: 2 | K97: Cash (Upon claiming on June 18) | M97: =if(K97="GGash",1,0) -> 0
A98: 45814.697 | B98: Bachelor of Science in Accountancy | C98: 4-A5 | D98: John Jericho D. Layug | E98: John Jericho Layug | F98: 7029 416 026821 | G98: https://drive.google.com/open?id=1fQicBis4xVCM5bmKnsHLzIar3H-1i4lO | H98: 09471944802 | J98: 1 | K98: GGash | M98: =if(K98="GGash",1,0) -> 1
A99: 45814.708 | B99: Bachelor of Science in Accountancy | C99: 4-A5 | D99: Thrisha M. De Torres | J99: 1 | K99: Cash (Upon claiming on June 18) | M99: =if(K99="GGash",1,0) -> 0
A100: 45814.721 | B100: Bachelor of Science in Accountancy | C100: 4-A6 | D100: Claire Ann Digamon | J100: 1 | K100: Cash (Upon claiming on June 18) | M100: =if(K100="GGash",1,0) -> 0
...

Sheet Order Total
A2: gcash | B2: PROGRAM | C2: NUMBER OF ORDERS | E2: overall | F2: PROGRAM | G2: NUMBER OF ORDERS
B3: Bachelor of Elementary Education (BEED) | C3: =SUMIF('Form Responses 1'!B:M,B3,'Form Responses 1'!M:M) -> 34 | F3: Bachelor of Elementary Education (BEED) | G3: =C3+C14 -> 96
B4: Bachelor of Secondary Education Major in English (BSED-E) | C4: =SUMIF('Form Responses 1'!B:M,B4,'Form Responses 1'!M:M) -> 39 | F4: Bachelor of Secondary Education Major in English (BSED-E) | G4: =C4+C15 -> 53
B5: Bachelor of Secondary Education Major in Science (BSED-S) | C5: =SUMIF('Form Responses 1'!B:M,B5,'Form Responses 1'!M:M) -> 5 | F5: Bachelor of Secondary Education Major in Science (BSED-S) | G5: =C5+C16 -> 23
B6: Bachelor of Secondary Education Major in Mathematics (BSED-M) | C6: =SUMIF('Form Responses 1'!B:M,B6,'Form Responses 1'!M:M) -> 2 | F6: Bachelor of Secondary Education Major in Mathematics (BSED-M) | G6: =C6+C17 -> 7
B7: Bachelor of Science in Accountancy | C7: =SUMIF('Form Responses 1'!B:M,B7,'Form Responses 1'!M:M) -> 14 | F7: Bachelor of Science in Accountancy | G7: =C7+C18 -> 48
B8: Bachelor of Science in Accounting Information System | C8: =SUMIF('Form Responses 1'!B:M,B8,'Form Responses 1'!M:M) -> 3 | F8: Bachelor of Science in Accounting Information System | G8: =C8+C19 -> 9
B9: Bachelor of Science in Information Technology | C9: =SUMIF('Form Responses 1'!B:M,B9,'Form Responses 1'!M:M) -> 28 | F9: Bachelor of Science in Information Technology | G9: =C9+C20 -> 45
B10: Bachelor of Science in Computer Science | C10: =SUMIF('Form Responses 1'!B:M,B10,'Form Responses 1'!M:M) -> 10 | F10: Bachelor of Science in Computer Science | G10: =C10+C21 -> 12
B11: OVERALL TOTAL | C11: =SUM(C3:C10) -> 135 | F11: OVERALL TOTAL | G11: =SUM(G3:G10) -> 293
A13: cash | B13: PROGRAM | C13: NUMBER OF ORDERS
B14: Bachelor of Elementary Education (BEED) | C14: =SUMIF('Form Responses 1'!B:M,B14,'Form Responses 1'!J:J) -> 62
B15: Bachelor of Secondary Education Major in English (BSED-E) | C15: =SUMIF('Form Responses 1'!B:M,B15,'Form Responses 1'!J:J) -> 14
B16: Bachelor of Secondary Education Major in Science (BSED-S) | C16: =SUMIF('Form Responses 1'!B:M,B16,'Form Responses 1'!J:J) -> 18
B17: Bachelor of Secondary Education Major in Mathematics (BSED-M) | C17: =SUMIF('Form Responses 1'!B:M,B17,'Form Responses 1'!J:J) -> 5
B18: Bachelor of Science in Accountancy | C18: =SUMIF('Form Responses 1'!B:M,B18,'Form Responses 1'!J:J) -> 34
B19: Bachelor of Science in Accounting Information System | C19: =SUMIF('Form Responses 1'!B:M,B19,'Form Responses 1'!J:J) -> 6
B20: Bachelor of Science in Information Technology | C20: =SUMIF('Form Responses 1'!B:M,B20,'Form Responses 1'!J:J) -> 17
B21: Bachelor of Science in Computer Science | C21: =SUMIF('Form Responses 1'!B:M,B21,'Form Responses 1'!J:J) -> 2
B22: OVERALL TOTAL | C22: =SUM(C14:C21) -> 158

Sheet SCF
B3: STATEMENT OF CASH FLOWS
B5: Incoming Payments | D5: =(260*5)+(50*(sum('Form Responses 1'!M:M))) -> 8050
B6: Refunds due to Price Change | D6: =(-210)*5 -> -1050
B7: Gcash received for Pre-Payment | E7: =SUM(D5:D6) -> 7000
B8: Cash to be received in June 18 | E8: =50*(SUM('Form Responses 1'!J:J)) -> 7900
B9: TOTAL AMOUNT | E9: =SUM(E8,E7) -> 14900
B11: Keychain Cost | C11: =1990*2+(1194)+995 -> 6169
B12: Bundle Deal Discount | C12: =-((90*2)+30+60) -> -270
B13: Payment Discount (ShopeePay) | C13: =-8*4 -> -32
B14: Shopee Voucher | C14: =-(400+400+250+215) -> -1265
B15: Shipping Fee | C15: =40*4 -> 160
B16: Shipping Discount | C16: =-40*4 -> -160 | D16: =SUM(C11:C16) -> 4602
B18: Transfer Costs
B19: Gcash to ShopeePay | C19: =15*2 -> 30
D20: =sum(C19:C20) -> 30 | E20: =sum(D16:D20) -> 4632 | F20: =E7-E20 -> 2368 | G20: =C80 -> 2351 | H20: =G20-F20 -> -17
B21: Gross Profit | E21: =E9-E20 -> 10268
D23: 1215 | E23: =E21/D23 -> 8.4510288
D24: PRICE | E24: # OF TRASH BINS
B60: ShopeePay balance
B61: Gcash to ShopeePay | D61: =726+15+3899 -> 4640
B62: Transfer Fee | D62: =-15*2 -> -30
B63: Received in ShopeePay | D63: =sum(D61:D62) -> 4610
B65: Payments
B66: Receipt 1 | C66: 876
B67: Receipt 2 | C67: 1492
B68: Receipt 3 | C68: 1492
B69: Receipt 4 | C69: =752-8 -> 744 | D69: =sum(C66:C70) -> 4604
B71: Remaining balance to be added to GCash Balance | D71: =D63-D69 -> 6
B73: GCash Balance
B74: Payment Received (net of refunds) | C74: =E7 -> 7000
B75: Gcash to ShopeePay | C75: =-3884-741 -> -4625
B76: Transfer Fee | C76: =D62 -> -30
B78: Remaining GCash after payment | C78: =SUM(C74:C76) -> 2345
B79: Add back: ShopeePay (sobra) | C79: =D71 -> 6
B80: Total Amount Remaining in GCash | C80: =C78+C79 -> 2351
